{
  "type": "minecraft:block",
  "functions": [
    {
      "function": "minecraft:explosion_decay"
    }
  ],
  "pools": [
    {
      "bonus_rolls": 0.0,
      "conditions": [
        {
          "block": "horticulture:onions",
          "condition": "minecraft:block_state_property",
          "properties": {
            "age": "2"
          }
        }
      ],
      "entries": [
        {
          "type": "minecraft:item",
          "name": "horticulture:onion"
        }
      ],
      "rolls": 1.0
    },
    {
      "bonus_rolls": 0.0,
      "conditions": [
        {
          "condition": "minecraft:inverted",
          "term": {
            "block": "horticulture:onions",
            "condition": "minecraft:block_state_property",
            "properties": {
              "age": "2"
            }
          }
        }
      ],
      "entries": [
        {
          "type": "minecraft:item",
          "name": "horticulture:onion_seeds"
        }
      ],
      "rolls": 1.0
    }
  ],
  "random_sequence": "horticulture:blocks/onions"
}